chalice_cognito_auth/__init__.py
chalice_cognito_auth/authorizer.py
chalice_cognito_auth/blueprint.py
chalice_cognito_auth/constants.py
chalice_cognito_auth/decoder.py
chalice_cognito_auth/exceptions.py
chalice_cognito_auth/userpool.py
chalice_cognito_auth/utils.py
chalice_cognito_auth-2.5.1.post3.dist-info/METADATA
chalice_cognito_auth-2.5.1.post3.dist-info/WHEEL
chalice_cognito_auth-2.5.1.post3.dist-info/top_level.txt
chalice_cognito_auth-2.5.1.post3.dist-info/RECORD
